{
	"fillColor":[255,0,0,128],
	"imageWidth":2048,
	"imageData":null,
	"imagePath":"2736_154942.jpg",
	"shapes":[
		{
			"flags":{},
			"shape_type":"rectangle",
			"label":"pet_bottles_clear",
			"line_color":{},
			"fill_color":{},
			"points":[
				[
					1035,
					0
				],
				[
					1511,
					321
				]
			]
		},
		{
			"flags":{},
			"shape_type":"rectangle",
			"label":"pet_bottles_clear",
			"line_color":{},
			"fill_color":{},
			"points":[
				[
					1508,
					1
				],
				[
					1827,
					405
				]
			]
		},
		{
			"flags":{},
			"shape_type":"rectangle",
			"label":"plastic_pots_tubs_trays",
			"line_color":{},
			"fill_color":{},
			"points":[
				[
					550,
					1158
				],
				[
					1432,
					1534
				]
			]
		},
		{
			"flags":{},
			"shape_type":"rectangle",
			"label":"plastic_pots_tubs_trays",
			"line_color":{},
			"fill_color":{},
			"points":[
				[
					822,
					286
				],
				[
					1288,
					596
				]
			]
		},
		{
			"flags":{},
			"shape_type":"rectangle",
			"label":"general_waste",
			"line_color":{},
			"fill_color":{},
			"points":[
				[
					540,
					585
				],
				[
					956,
					897
				]
			]
		},
		{
			"flags":{},
			"shape_type":"rectangle",
			"label":"fines",
			"line_color":{},
			"fill_color":{},
			"points":[
				[
					1426,
					919
				],
				[
					1500,
					1012
				]
			]
		}
	],
	"flags":{},
	"lineColor":[0,255,0,128],
	"version":"LMAI",
	"imageHeight":1536
}