{
	"fillColor":[255,0,0,128],
	"imageWidth":2048,
	"imageData":null,
	"imagePath":"3153_775836.jpg",
	"shapes":[
		{
			"flags":{},
			"shape_type":"rectangle",
			"label":"pet_bottles_clear",
			"line_color":{},
			"fill_color":{},
			"points":[
				[
					1158,
					27
				],
				[
					1632,
					623
				]
			]
		},
		{
			"flags":{},
			"shape_type":"rectangle",
			"label":"fines",
			"line_color":{},
			"fill_color":{},
			"points":[
				[
					1838,
					1285
				],
				[
					1895,
					1342
				]
			]
		},
		{
			"flags":{},
			"shape_type":"rectangle",
			"label":"fines",
			"line_color":{},
			"fill_color":{},
			"points":[
				[
					588,
					159
				],
				[
					640,
					218
				]
			]
		}
	],
	"flags":{},
	"lineColor":[0,255,0,128],
	"version":"LMAI",
	"imageHeight":1536
}