{
	"fillColor":[255,0,0,128],
	"imageWidth":2048,
	"imageData":null,
	"imagePath":"5245_640554.jpg",
	"shapes":[
		{
			"flags":{},
			"shape_type":"rectangle",
			"label":"plastic_pots_tubs_trays",
			"line_color":{},
			"fill_color":{},
			"points":[
				[
					696,
					1102
				],
				[
					957,
					1423
				]
			]
		},
		{
			"flags":{},
			"shape_type":"rectangle",
			"label":"plastic_pots_tubs_trays",
			"line_color":{},
			"fill_color":{},
			"points":[
				[
					896,
					0
				],
				[
					1365,
					485
				]
			]
		},
		{
			"flags":{},
			"shape_type":"rectangle",
			"label":"office_paper",
			"line_color":{},
			"fill_color":{},
			"points":[
				[
					1379,
					87
				],
				[
					1627,
					324
				]
			]
		},
		{
			"flags":{},
			"shape_type":"rectangle",
			"label":"hdpe_bottles_natural",
			"line_color":{},
			"fill_color":{},
			"points":[
				[
					1072,
					0
				],
				[
					1475,
					195
				]
			]
		},
		{
			"flags":{},
			"shape_type":"rectangle",
			"label":"pet_bottles_clear",
			"line_color":{},
			"fill_color":{},
			"points":[
				[
					292,
					0
				],
				[
					748,
					213
				]
			]
		},
		{
			"flags":{},
			"shape_type":"rectangle",
			"label":"pet_bottles_clear",
			"line_color":{},
			"fill_color":{},
			"points":[
				[
					587,
					370
				],
				[
					1179,
					788
				]
			]
		},
		{
			"flags":{},
			"shape_type":"rectangle",
			"label":"fines",
			"line_color":{},
			"fill_color":{},
			"points":[
				[
					1246,
					645
				],
				[
					1335,
					711
				]
			]
		},
		{
			"flags":{},
			"shape_type":"rectangle",
			"label":"flexible_film",
			"line_color":{},
			"fill_color":{},
			"points":[
				[
					904,
					737
				],
				[
					1009,
					850
				]
			]
		}
	],
	"flags":{},
	"lineColor":[0,255,0,128],
	"version":"LMAI",
	"imageHeight":1536
}