{
	"fillColor":[255,0,0,128],
	"imageWidth":2048,
	"imageData":null,
	"imagePath":"1017_180370.jpg",
	"shapes":[
		{
			"flags":{},
			"shape_type":"rectangle",
			"label":"pet_bottles_clear",
			"line_color":{},
			"fill_color":{},
			"points":[
				[
					800,
					318
				],
				[
					1521,
					907
				]
			]
		},
		{
			"flags":{},
			"shape_type":"rectangle",
			"label":"grey_board",
			"line_color":{},
			"fill_color":{},
			"points":[
				[
					1019,
					775
				],
				[
					1223,
					1099
				]
			]
		},
		{
			"flags":{},
			"shape_type":"rectangle",
			"label":"general_waste",
			"line_color":{},
			"fill_color":{},
			"points":[
				[
					911,
					954
				],
				[
					1052,
					1129
				]
			]
		},
		{
			"flags":{},
			"shape_type":"rectangle",
			"label":"plastic_pots_tubs_trays",
			"line_color":{},
			"fill_color":{},
			"points":[
				[
					1296,
					2
				],
				[
					1724,
					425
				]
			]
		},
		{
			"flags":{},
			"shape_type":"rectangle",
			"label":"general_waste",
			"line_color":{},
			"fill_color":{},
			"points":[
				[
					1318,
					0
				],
				[
					1611,
					171
				]
			]
		}
	],
	"flags":{},
	"lineColor":[0,255,0,128],
	"version":"LMAI",
	"imageHeight":1536
}