{
	"fillColor":[255,0,0,128],
	"imageWidth":2048,
	"imageData":null,
	"imagePath":"1033_901627.jpg",
	"shapes":[
		{
			"flags":{},
			"shape_type":"rectangle",
			"label":"grey_board",
			"line_color":{},
			"fill_color":{},
			"points":[
				[
					1259,
					1105
				],
				[
					1592,
					1534
				]
			]
		},
		{
			"flags":{},
			"shape_type":"rectangle",
			"label":"brown_board",
			"line_color":{},
			"fill_color":{},
			"points":[
				[
					500,
					599
				],
				[
					726,
					758
				]
			]
		},
		{
			"flags":{},
			"shape_type":"rectangle",
			"label":"fines",
			"line_color":{},
			"fill_color":{},
			"points":[
				[
					284,
					835
				],
				[
					347,
					1018
				]
			]
		},
		{
			"flags":{},
			"shape_type":"rectangle",
			"label":"pet_bottles_clear",
			"line_color":{},
			"fill_color":{},
			"points":[
				[
					778,
					162
				],
				[
					1328,
					683
				]
			]
		},
		{
			"flags":{},
			"shape_type":"rectangle",
			"label":"pet_bottles_clear",
			"line_color":{},
			"fill_color":{},
			"points":[
				[
					1035,
					0
				],
				[
					1631,
					192
				]
			]
		},
		{
			"flags":{},
			"shape_type":"rectangle",
			"label":"office_paper",
			"line_color":{},
			"fill_color":{},
			"points":[
				[
					671,
					0
				],
				[
					1191,
					340
				]
			]
		},
		{
			"flags":{},
			"shape_type":"rectangle",
			"label":"general_waste",
			"line_color":{},
			"fill_color":{},
			"points":[
				[
					1444,
					1011
				],
				[
					1600,
					1156
				]
			]
		}
	],
	"flags":{},
	"lineColor":[0,255,0,128],
	"version":"LMAI",
	"imageHeight":1536
}