{
	"fillColor":[255,0,0,128],
	"imageWidth":2048,
	"imageData":null,
	"imagePath":"1304_698246.jpg",
	"shapes":[
		{
			"flags":{},
			"shape_type":"rectangle",
			"label":"aluminium_cans",
			"line_color":{},
			"fill_color":{},
			"points":[
				[
					284,
					933
				],
				[
					508,
					1146
				]
			]
		},
		{
			"flags":{},
			"shape_type":"rectangle",
			"label":"drink_cartons",
			"line_color":{},
			"fill_color":{},
			"points":[
				[
					478,
					856
				],
				[
					1054,
					1256
				]
			]
		},
		{
			"flags":{},
			"shape_type":"rectangle",
			"label":"pet_bottles_clear",
			"line_color":{},
			"fill_color":{},
			"points":[
				[
					714,
					414
				],
				[
					1155,
					1054
				]
			]
		},
		{
			"flags":{},
			"shape_type":"rectangle",
			"label":"pet_bottles_clear",
			"line_color":{},
			"fill_color":{},
			"points":[
				[
					370,
					102
				],
				[
					822,
					543
				]
			]
		},
		{
			"flags":{},
			"shape_type":"rectangle",
			"label":"hdpe_bottles_natural",
			"line_color":{},
			"fill_color":{},
			"points":[
				[
					560,
					0
				],
				[
					1060,
					717
				]
			]
		},
		{
			"flags":{},
			"shape_type":"rectangle",
			"label":"general_waste",
			"line_color":{},
			"fill_color":{},
			"points":[
				[
					938,
					606
				],
				[
					1651,
					961
				]
			]
		}
	],
	"flags":{},
	"lineColor":[0,255,0,128],
	"version":"LMAI",
	"imageHeight":1536
}