{
	"fillColor":[255,0,0,128],
	"imageWidth":2048,
	"imageData":null,
	"imagePath":"4010_658214.jpg",
	"shapes":[
		{
			"flags":{},
			"shape_type":"rectangle",
			"label":"pet_bottles_clear",
			"line_color":{},
			"fill_color":{},
			"points":[
				[
					822,
					606
				],
				[
					1608,
					1087
				]
			]
		},
		{
			"flags":{},
			"shape_type":"rectangle",
			"label":"plastic_pots_tubs_trays",
			"line_color":{},
			"fill_color":{},
			"points":[
				[
					866,
					849
				],
				[
					1146,
					1116
				]
			]
		},
		{
			"flags":{},
			"shape_type":"rectangle",
			"label":"plastic_bottles_coloured",
			"line_color":{},
			"fill_color":{},
			"points":[
				[
					756,
					102
				],
				[
					1198,
					375
				]
			]
		},
		{
			"flags":{},
			"shape_type":"rectangle",
			"label":"pet_bottles_clear",
			"line_color":{},
			"fill_color":{},
			"points":[
				[
					1183,
					3
				],
				[
					1640,
					333
				]
			]
		},
		{
			"flags":{},
			"shape_type":"rectangle",
			"label":"aluminium_cans",
			"line_color":{},
			"fill_color":{},
			"points":[
				[
					219,
					1167
				],
				[
					471,
					1503
				]
			]
		},
		{
			"flags":{},
			"shape_type":"rectangle",
			"label":"fines",
			"line_color":{},
			"fill_color":{},
			"points":[
				[
					800,
					1264
				],
				[
					888,
					1344
				]
			]
		}
	],
	"flags":{},
	"lineColor":[0,255,0,128],
	"version":"LMAI",
	"imageHeight":1536
}