{
    "shapes": [
        {
            "shape_type": "polygon",
            "points": [
                [
                    133.7072292884948,
                    275.38951743046033
                ],
                [
                    272.9545411164518,
                    277.27123786056785
                ],
                [
                    265.96529380462385,
                    224.5830658175571
                ],
                [
                    160.0513153100002,
                    222.70134538744958
                ]
            ],
            "flags": {},
            "group_id": null,
            "label": "pickable_smartpac"
        },
        {
            "shape_type": "polygon",
            "points": [
                [
                    173.38538787455514,
                    172.0787766214766
                ],
                [
                    275.95861130149126,
                    182.85393595154918
                ],
                [
                    279.81844644189556,
                    94.81879782748267
                ],
                [
                    182.0242232485432,
                    87.0411618205288
                ]
            ],
            "flags": {},
            "group_id": null,
            "label": "pickable_flat"
        },
        {
            "shape_type": "polygon",
            "points": [
                [
                    279.682982944061,
                    112.64984072665189
                ],
                [
                    338.36066889447426,
                    128.07683797183094
                ],
                [
                    359.57279010659545,
                    39.09612171838743
                ],
                [
                    301.44606834351003,
                    24.220088660536184
                ]
            ],
            "flags": {},
            "group_id": null,
            "label": "pickable_box"
        },
        {
            "shape_type": "polygon",
            "points": [
                [
                    348.4408907158865,
                    139.0337568795938
                ],
                [
                    351.8592914840059,
                    259.7572787431808
                ],
                [
                    465.0321811745148,
                    254.43473138628343
                ],
                [
                    462.3276110432346,
                    135.79033659442047
                ]
            ],
            "flags": {},
            "group_id": null,
            "label": "pickable_smartpac"
        }
    ],
    "imagePath": "1616051585-513649-por1094.png",
    "flags": {},
    "imageWidth": 640,
    "imageHeight": 360
}