{
    "shapes": [
        {
            "shape_type": "polygon",
            "points": [
                [
                    116.89619296787131,
                    110.45036432099369
                ],
                [
                    88.4271847034085,
                    213.61565357719203
                ],
                [
                    205.46644090175562,
                    249.29333952760527
                ],
                [
                    236.73090371167297,
                    139.58259572595236
                ]
            ],
            "flags": {},
            "group_id": null,
            "label": "pickable_smartpac"
        },
        {
            "shape_type": "polygon",
            "points": [
                [
                    257.6045219423107,
                    80.7916657123526
                ],
                [
                    251.60452194231075,
                    133.5416657123526
                ],
                [
                    340.8545219423107,
                    142.2916657123526
                ],
                [
                    345.6045219423107,
                    88.2916657123526
                ]
            ],
            "flags": {},
            "group_id": null,
            "label": "pickable_box"
        },
        {
            "shape_type": "polygon",
            "points": [
                [
                    349.28341281887595,
                    48.93612009517907
                ],
                [
                    372.1045219423107,
                    142.7916657123526
                ],
                [
                    460.49801306657105,
                    121.03426926264846
                ],
                [
                    438.6045219423107,
                    27.54314500229341
                ]
            ],
            "flags": {},
            "group_id": null,
            "label": "pickable_box"
        },
        {
            "shape_type": "polygon",
            "points": [
                [
                    367.4443824177176,
                    139.18016293760087
                ],
                [
                    362.8856042195951,
                    260.1105258351769
                ],
                [
                    465.5892612183341,
                    258.9217910726717
                ],
                [
                    461.2176765188805,
                    137.61031566283557
                ]
            ],
            "flags": {},
            "group_id": null,
            "label": "pickable_smartpac"
        },
        {
            "shape_type": "polygon",
            "points": [
                [
                    469.1070163294035,
                    109.34967747556053
                ],
                [
                    564.2227232835917,
                    26.292565558803627
                ],
                [
                    639.4092904477708,
                    113.79256555880362
                ],
                [
                    551.5361561194126,
                    199.61346108119164
                ]
            ],
            "flags": {},
            "group_id": null,
            "label": "pickable_smartpac"
        }
    ],
    "imagePath": "1616067062-376943-por1094.png",
    "flags": {},
    "imageWidth": 640,
    "imageHeight": 360
}