{
    "shapes": [
        {
            "shape_type": "polygon",
            "points": [
                [
                    465.1087769099838,
                    150.33403242370082
                ],
                [
                    471.7203471579177,
                    211.28444564684133
                ],
                [
                    379.7781983975871,
                    217.27618118403137
                ],
                [
                    375.4393554223805,
                    158.39188366337024
                ]
            ],
            "flags": {},
            "group_id": null,
            "label": "pickable_box"
        },
        {
            "shape_type": "polygon",
            "points": [
                [
                    415.1087769099838,
                    62.11089192783305
                ],
                [
                    373.1666281496532,
                    167.06956961378347
                ],
                [
                    240.7286116207276,
                    119.54890845675867
                ],
                [
                    261.1831570752731,
                    0
                ]
            ],
            "flags": {},
            "group_id": null,
            "label": "pickable_flat"
        },
        {
            "shape_type": "polygon",
            "points": [
                [
                    240.73431405242945,
                    192.98878899431728
                ],
                [
                    169.8200864775642,
                    286.89053146854775
                ],
                [
                    61.32256085405619,
                    207.2575965646042
                ],
                [
                    134.8857792448608,
                    123.92426323127088
                ]
            ],
            "flags": {},
            "group_id": null,
            "label": "pickable_smartpac"
        },
        {
            "shape_type": "polygon",
            "points": [
                [
                    116.02274068483295,
                    111.85857389377189
                ],
                [
                    196.23326700062242,
                    169.12173178850873
                ],
                [
                    236.02274068483294,
                    117.75331073587715
                ],
                [
                    157.48367818483294,
                    61.37789955166664
                ]
            ],
            "flags": {},
            "group_id": null,
            "label": "pickable_box"
        }
    ],
    "imagePath": "1616051563-771053-por1094.png",
    "flags": {},
    "imageWidth": 640,
    "imageHeight": 360
}