{
    "shapes": [
        {
            "shape_type": "polygon",
            "points": [
                [
                    357.290439972089,
                    92.39588101949931
                ],
                [
                    392.41440691423776,
                    197.5611702756977
                ],
                [
                    469.27391104646915,
                    169.87521986247455
                ],
                [
                    438.07556393903116,
                    72.14794713520182
                ]
            ],
            "flags": {},
            "group_id": null,
            "label": "pickable_flat"
        },
        {
            "shape_type": "polygon",
            "points": [
                [
                    273.82153612015406,
                    164.83005442236325
                ],
                [
                    282.09076688938484,
                    264.2531313454402
                ],
                [
                    413.82153612015406,
                    260.4069774992863
                ],
                [
                    403.43692073553865,
                    150.2146698069786
                ]
            ],
            "flags": {},
            "group_id": null,
            "label": "pickable_polybag"
        }
    ],
    "imagePath": "1619258459-986808-por1094.png",
    "flags": {},
    "imageWidth": 640,
    "imageHeight": 360
}