{
    "shapes": [
        {
            "shape_type": "polygon",
            "points": [
                [
                    209.45873749906008,
                    139.38277314083766
                ],
                [
                    289.8350815850816,
                    207.12470862470863
                ],
                [
                    240.6415331979848,
                    266.8021279795473
                ],
                [
                    159.45873749906008,
                    200.13546131288066
                ]
            ],
            "flags": {},
            "group_id": null,
            "label": "pickable_box"
        },
        {
            "shape_type": "polygon",
            "points": [
                [
                    358.9211030904579,
                    49.32900969997745
                ],
                [
                    345.48024287540414,
                    172.4472892698699
                ],
                [
                    453.27594180013534,
                    179.97417099030002
                ],
                [
                    466.44798481088804,
                    59.00642905481616
                ]
            ],
            "flags": {},
            "group_id": null,
            "label": "pickable_smartpac"
        },
        {
            "shape_type": "polygon",
            "points": [
                [
                    249.78131814422136,
                    24.866644108579603
                ],
                [
                    201.66303857432888,
                    120.29675163546132
                ],
                [
                    309.9963719076622,
                    180.78062260320326
                ],
                [
                    353.5447590044364,
                    92.3397623881495
                ]
            ],
            "flags": {},
            "group_id": null,
            "label": "pickable_smartpac"
        }
    ],
    "imagePath": "1619258710-107101-por1094.png",
    "flags": {},
    "imageWidth": 640,
    "imageHeight": 360
}