{
    "shapes": [
        {
            "shape_type": "polygon",
            "points": [
                [
                    346.44805895285253,
                    156.85061629850708
                ],
                [
                    466.05172019874254,
                    148.24846576087268
                ],
                [
                    470.62161267186076,
                    260.6140571587221
                ],
                [
                    352.87967718798984,
                    260.2008340182263
                ]
            ],
            "flags": {},
            "group_id": null,
            "label": "pickable_smartpac"
        }
    ],
    "imagePath": "1619257720-635816-por1094.png",
    "flags": {},
    "imageWidth": 640,
    "imageHeight": 360
}