{
    "shapes": [
        {
            "shape_type": "polygon",
            "points": [
                [
                    123.68679397525548,
                    167.41984938138785
                ],
                [
                    246.8295114728117,
                    159.7012239208269
                ],
                [
                    244.6789738384031,
                    264.27111639394514
                ],
                [
                    130.96929641904828,
                    270.1850948885688
                ]
            ],
            "flags": {},
            "group_id": null,
            "label": "pickable_smartpac"
        },
        {
            "shape_type": "polygon",
            "points": [
                [
                    319.14133942980095,
                    145.4539120928699
                ],
                [
                    424.2488663115214,
                    106.20660026491294
                ],
                [
                    468.3348878168977,
                    220.72272929717099
                ],
                [
                    364.0338125480805,
                    261.3141271466333
                ]
            ],
            "flags": {},
            "group_id": null,
            "label": "pickable_smartpac"
        }
    ],
    "imagePath": "1619258517-864067-por1094.png",
    "flags": {},
    "imageWidth": 640,
    "imageHeight": 360
}