{
	"fillColor":[255,0,0,128],
	"imageWidth":2048,
	"imageData":null,
	"imagePath":"0238_911383.jpg",
	"shapes":[
		{
			"flags":{},
			"shape_type":"rectangle",
			"label":"plastic_bottles_coloured",
			"line_color":{},
			"fill_color":{},
			"points":[
				[
					678,
					692
				],
				[
					1251,
					1252
				]
			]
		},
		{
			"flags":{},
			"shape_type":"rectangle",
			"label":"pet_bottles_clear",
			"line_color":{},
			"fill_color":{},
			"points":[
				[
					971,
					1
				],
				[
					1260,
					266
				]
			]
		},
		{
			"flags":{},
			"shape_type":"rectangle",
			"label":"pet_bottles_clear",
			"line_color":{},
			"fill_color":{},
			"points":[
				[
					1139,
					8
				],
				[
					1551,
					494
				]
			]
		},
		{
			"flags":{},
			"shape_type":"rectangle",
			"label":"pet_bottles_clear",
			"line_color":{},
			"fill_color":{},
			"points":[
				[
					1434,
					452
				],
				[
					1776,
					889
				]
			]
		},
		{
			"flags":{},
			"shape_type":"rectangle",
			"label":"aluminium_cans",
			"line_color":{},
			"fill_color":{},
			"points":[
				[
					1504,
					228
				],
				[
					1724,
					404
				]
			]
		},
		{
			"flags":{},
			"shape_type":"rectangle",
			"label":"pet_bottles_clear",
			"line_color":{},
			"fill_color":{},
			"points":[
				[
					1508,
					1
				],
				[
					1711,
					217
				]
			]
		},
		{
			"flags":{},
			"shape_type":"rectangle",
			"label":"pet_bottles_clear",
			"line_color":{},
			"fill_color":{},
			"points":[
				[
					443,
					19
				],
				[
					960,
					944
				]
			]
		},
		{
			"flags":{},
			"shape_type":"rectangle",
			"label":"pet_bottles_clear",
			"line_color":{},
			"fill_color":{},
			"points":[
				[
					1246,
					575
				],
				[
					1571,
					1022
				]
			]
		},
		{
			"flags":{},
			"shape_type":"rectangle",
			"label":"plastic_pots_tubs_trays",
			"line_color":{},
			"fill_color":{},
			"points":[
				[
					1320,
					852
				],
				[
					1672,
					1353
				]
			]
		},
		{
			"flags":{},
			"shape_type":"rectangle",
			"label":"pet_bottles_clear",
			"line_color":{},
			"fill_color":{},
			"points":[
				[
					544,
					587
				],
				[
					1495,
					1456
				]
			]
		},
		{
			"flags":{},
			"shape_type":"rectangle",
			"label":"pet_bottles_clear",
			"line_color":{},
			"fill_color":{},
			"points":[
				[
					826,
					1248
				],
				[
					1024,
					1533
				]
			]
		}
	],
	"flags":{},
	"lineColor":[0,255,0,128],
	"version":"LMAI",
	"imageHeight":1536
}