{
	"fillColor":[255,0,0,128],
	"imageWidth":2048,
	"imageData":null,
	"imagePath":"1619_639484.jpg",
	"shapes":[
		{
			"flags":{},
			"shape_type":"rectangle",
			"label":"grey_board",
			"line_color":{},
			"fill_color":{},
			"points":[
				[
					872,
					525
				],
				[
					1316,
					865
				]
			]
		},
		{
			"flags":{},
			"shape_type":"rectangle",
			"label":"newspaper",
			"line_color":{},
			"fill_color":{},
			"points":[
				[
					1230,
					277
				],
				[
					1830,
					1356
				]
			]
		},
		{
			"flags":{},
			"shape_type":"rectangle",
			"label":"grey_board",
			"line_color":{},
			"fill_color":{},
			"points":[
				[
					804,
					45
				],
				[
					1724,
					839
				]
			]
		},
		{
			"flags":{},
			"shape_type":"rectangle",
			"label":"pet_bottles_clear",
			"line_color":{},
			"fill_color":{},
			"points":[
				[
					842,
					1372
				],
				[
					1004,
					1534
				]
			]
		},
		{
			"flags":{},
			"shape_type":"rectangle",
			"label":"plastic_pots_tubs_trays",
			"line_color":{},
			"fill_color":{},
			"points":[
				[
					1227,
					1059
				],
				[
					1676,
					1534
				]
			]
		},
		{
			"flags":{},
			"shape_type":"rectangle",
			"label":"plastic_pots_tubs_trays",
			"line_color":{},
			"fill_color":{},
			"points":[
				[
					446,
					843
				],
				[
					1230,
					1243
				]
			]
		},
		{
			"flags":{},
			"shape_type":"rectangle",
			"label":"pet_bottles_clear",
			"line_color":{},
			"fill_color":{},
			"points":[
				[
					1119,
					955
				],
				[
					1441,
					1345
				]
			]
		},
		{
			"flags":{},
			"shape_type":"rectangle",
			"label":"general_waste",
			"line_color":{},
			"fill_color":{},
			"points":[
				[
					516,
					1150
				],
				[
					986,
					1518
				]
			]
		},
		{
			"flags":{},
			"shape_type":"rectangle",
			"label":"general_waste",
			"line_color":{},
			"fill_color":{},
			"points":[
				[
					638,
					336
				],
				[
					1064,
					753
				]
			]
		},
		{
			"flags":{},
			"shape_type":"rectangle",
			"label":"aluminium_cans",
			"line_color":{},
			"fill_color":{},
			"points":[
				[
					918,
					408
				],
				[
					1107,
					591
				]
			]
		},
		{
			"flags":{},
			"shape_type":"rectangle",
			"label":"aluminium_cans",
			"line_color":{},
			"fill_color":{},
			"points":[
				[
					746,
					597
				],
				[
					899,
					733
				]
			]
		}
	],
	"flags":{},
	"lineColor":[0,255,0,128],
	"version":"LMAI",
	"imageHeight":1536
}