{
	"fillColor":[255,0,0,128],
	"imageWidth":2048,
	"imageData":null,
	"imagePath":"1704_500331.jpg",
	"shapes":[
		{
			"flags":{},
			"shape_type":"rectangle",
			"label":"pet_bottles_clear",
			"line_color":{},
			"fill_color":{},
			"points":[
				[
					672,
					964
				],
				[
					916,
					1444
				]
			]
		},
		{
			"flags":{},
			"shape_type":"rectangle",
			"label":"pet_bottles_clear",
			"line_color":{},
			"fill_color":{},
			"points":[
				[
					1019,
					1099
				],
				[
					1327,
					1534
				]
			]
		},
		{
			"flags":{},
			"shape_type":"rectangle",
			"label":"flexible_film",
			"line_color":{},
			"fill_color":{},
			"points":[
				[
					1214,
					1213
				],
				[
					1598,
					1532
				]
			]
		},
		{
			"flags":{},
			"shape_type":"rectangle",
			"label":"pet_bottles_clear",
			"line_color":{},
			"fill_color":{},
			"points":[
				[
					731,
					58
				],
				[
					1011,
					458
				]
			]
		},
		{
			"flags":{},
			"shape_type":"rectangle",
			"label":"fines",
			"line_color":{},
			"fill_color":{},
			"points":[
				[
					1232,
					549
				],
				[
					1312,
					609
				]
			]
		},
		{
			"flags":{},
			"shape_type":"rectangle",
			"label":"fines",
			"line_color":{},
			"fill_color":{},
			"points":[
				[
					1494,
					1261
				],
				[
					1586,
					1349
				]
			]
		}
	],
	"flags":{},
	"lineColor":[0,255,0,128],
	"version":"LMAI",
	"imageHeight":1536
}