{
	"fillColor":[255,0,0,128],
	"imageWidth":2048,
	"imageData":null,
	"imagePath":"2134_838571.jpg",
	"shapes":[
		{
			"flags":{},
			"shape_type":"rectangle",
			"label":"general_waste",
			"line_color":{},
			"fill_color":{},
			"points":[
				[
					1234,
					564
				],
				[
					1376,
					678
				]
			]
		},
		{
			"flags":{},
			"shape_type":"rectangle",
			"label":"general_waste",
			"line_color":{},
			"fill_color":{},
			"points":[
				[
					1714,
					1369
				],
				[
					1802,
					1474
				]
			]
		},
		{
			"flags":{},
			"shape_type":"rectangle",
			"label":"pet_bottles_clear",
			"line_color":{},
			"fill_color":{},
			"points":[
				[
					666,
					1063
				],
				[
					1224,
					1534
				]
			]
		},
		{
			"flags":{},
			"shape_type":"rectangle",
			"label":"flexible_film",
			"line_color":{},
			"fill_color":{},
			"points":[
				[
					504,
					1273
				],
				[
					1238,
					1532
				]
			]
		}
	],
	"flags":{},
	"lineColor":[0,255,0,128],
	"version":"LMAI",
	"imageHeight":1536
}