{
	"fillColor":[255,0,0,128],
	"imageWidth":2048,
	"imageData":null,
	"imagePath":"2158_363524.jpg",
	"shapes":[
		{
			"flags":{},
			"shape_type":"rectangle",
			"label":"pet_bottles_clear",
			"line_color":{},
			"fill_color":{},
			"points":[
				[
					863,
					698
				],
				[
					1539,
					971
				]
			]
		},
		{
			"flags":{},
			"shape_type":"rectangle",
			"label":"plastic_pots_tubs_trays",
			"line_color":{},
			"fill_color":{},
			"points":[
				[
					968,
					1128
				],
				[
					1252,
					1534
				]
			]
		},
		{
			"flags":{},
			"shape_type":"rectangle",
			"label":"pet_bottles_clear",
			"line_color":{},
			"fill_color":{},
			"points":[
				[
					1255,
					1303
				],
				[
					1731,
					1534
				]
			]
		},
		{
			"flags":{},
			"shape_type":"rectangle",
			"label":"plastic_bottles_coloured",
			"line_color":{},
			"fill_color":{},
			"points":[
				[
					934,
					150
				],
				[
					1146,
					417
				]
			]
		},
		{
			"flags":{},
			"shape_type":"rectangle",
			"label":"pet_bottles_clear",
			"line_color":{},
			"fill_color":{},
			"points":[
				[
					1387,
					298
				],
				[
					1797,
					668
				]
			]
		},
		{
			"flags":{},
			"shape_type":"rectangle",
			"label":"pet_bottles_clear",
			"line_color":{},
			"fill_color":{},
			"points":[
				[
					1136,
					0
				],
				[
					1577,
					438
				]
			]
		}
	],
	"flags":{},
	"lineColor":[0,255,0,128],
	"version":"LMAI",
	"imageHeight":1536
}