{
	"fillColor":[255,0,0,128],
	"imageWidth":2048,
	"imageData":null,
	"imagePath":"3357_767384.jpg",
	"shapes":[
		{
			"flags":{},
			"shape_type":"rectangle",
			"label":"pet_bottles_clear",
			"line_color":{},
			"fill_color":{},
			"points":[
				[
					800,
					13
				],
				[
					1652,
					554
				]
			]
		},
		{
			"flags":{},
			"shape_type":"rectangle",
			"label":"pet_bottles_clear",
			"line_color":{},
			"fill_color":{},
			"points":[
				[
					803,
					321
				],
				[
					1011,
					808
				]
			]
		},
		{
			"flags":{},
			"shape_type":"rectangle",
			"label":"general_waste",
			"line_color":{},
			"fill_color":{},
			"points":[
				[
					1212,
					495
				],
				[
					1611,
					859
				]
			]
		},
		{
			"flags":{},
			"shape_type":"rectangle",
			"label":"plastic_pots_tubs_trays",
			"line_color":{},
			"fill_color":{},
			"points":[
				[
					1436,
					952
				],
				[
					1700,
					1285
				]
			]
		}
	],
	"flags":{},
	"lineColor":[0,255,0,128],
	"version":"LMAI",
	"imageHeight":1536
}