{
	"fillColor":[255,0,0,128],
	"imageWidth":2048,
	"imageData":null,
	"imagePath":"3710_966855.jpg",
	"shapes":[
		{
			"flags":{},
			"shape_type":"rectangle",
			"label":"general_waste",
			"line_color":{},
			"fill_color":{},
			"points":[
				[
					760,
					3
				],
				[
					1180,
					276
				]
			]
		},
		{
			"flags":{},
			"shape_type":"rectangle",
			"label":"pet_bottles_clear",
			"line_color":{},
			"fill_color":{},
			"points":[
				[
					444,
					250
				],
				[
					936,
					832
				]
			]
		},
		{
			"flags":{},
			"shape_type":"rectangle",
			"label":"pet_bottles_clear",
			"line_color":{},
			"fill_color":{},
			"points":[
				[
					1103,
					561
				],
				[
					1599,
					786
				]
			]
		},
		{
			"flags":{},
			"shape_type":"rectangle",
			"label":"pet_bottles_clear",
			"line_color":{},
			"fill_color":{},
			"points":[
				[
					1375,
					1281
				],
				[
					1589,
					1534
				]
			]
		},
		{
			"flags":{},
			"shape_type":"rectangle",
			"label":"flexible_film",
			"line_color":{},
			"fill_color":{},
			"points":[
				[
					1588,
					214
				],
				[
					1851,
					428
				]
			]
		},
		{
			"flags":{},
			"shape_type":"rectangle",
			"label":"flexible_film",
			"line_color":{},
			"fill_color":{},
			"points":[
				[
					408,
					459
				],
				[
					1824,
					1419
				]
			]
		}
	],
	"flags":{},
	"lineColor":[0,255,0,128],
	"version":"LMAI",
	"imageHeight":1536
}