{
	"fillColor":[255,0,0,128],
	"imageWidth":2048,
	"imageData":null,
	"imagePath":"4911_109243.jpg",
	"shapes":[
		{
			"flags":{},
			"shape_type":"rectangle",
			"label":"pet_bottles_clear",
			"line_color":{},
			"fill_color":{},
			"points":[
				[
					880,
					376
				],
				[
					1395,
					1057
				]
			]
		},
		{
			"flags":{},
			"shape_type":"rectangle",
			"label":"pet_bottles_clear",
			"line_color":{},
			"fill_color":{},
			"points":[
				[
					856,
					0
				],
				[
					1200,
					247
				]
			]
		},
		{
			"flags":{},
			"shape_type":"rectangle",
			"label":"hdpe_bottles_natural",
			"line_color":{},
			"fill_color":{},
			"points":[
				[
					1436,
					0
				],
				[
					1668,
					76
				]
			]
		},
		{
			"flags":{},
			"shape_type":"rectangle",
			"label":"newspaper",
			"line_color":{},
			"fill_color":{},
			"points":[
				[
					862,
					1099
				],
				[
					1120,
					1477
				]
			]
		}
	],
	"flags":{},
	"lineColor":[0,255,0,128],
	"version":"LMAI",
	"imageHeight":1536
}